pyaf/ForecastEngine.py
pyaf/HierarchicalForecastEngine.py
pyaf/__init__.py
pyaf/Bench/Artificial.py
pyaf/Bench/GenericBenchmark.py
pyaf/Bench/MComp.py
pyaf/Bench/NN3.py
pyaf/Bench/TS_datasets.py
pyaf/Bench/YahooStocks.py
pyaf/Bench/__init__.py
pyaf/Bench/download_all_stock_prices.py
pyaf/Bench/stocks_symbol_list.py
pyaf/TS/Complexity.py
pyaf/TS/DateTime_Functions.py
pyaf/TS/Exogenous.py
pyaf/TS/Intermittent_Models.py
pyaf/TS/Keras_Models.py
pyaf/TS/MissingData.py
pyaf/TS/ModelSelection_Legacy.py
pyaf/TS/ModelSelection_Voting.py
pyaf/TS/Options.py
pyaf/TS/Perf.py
pyaf/TS/Plots.py
pyaf/TS/PredictionIntervals.py
pyaf/TS/Pytorch_Models.py
pyaf/TS/Scikit_Models.py
pyaf/TS/SignalDecomposition.py
pyaf/TS/SignalDecomposition_AR.py
pyaf/TS/SignalDecomposition_Cycle.py
pyaf/TS/SignalDecomposition_Forecaster.py
pyaf/TS/SignalDecomposition_Trainer.py
pyaf/TS/SignalDecomposition_Trend.py
pyaf/TS/SignalHierarchy.py
pyaf/TS/Signal_Grouping.py
pyaf/TS/Signal_Transformation.py
pyaf/TS/Temporal_Hierarchy.py
pyaf/TS/Time.py
pyaf/TS/TimeSeriesModel.py
pyaf/TS/TimeSeries_Cutting.py
pyaf/TS/Utils.py
pyaf/TS/__init__.py
pyaf/WS/WS_Backend.py
pyaf/WS/WS_REST_Flask.py
pyaf/WS/__init__.py
pyaf/WS/test_heroku_web_service.py
pyaf-5.0.dist-info/AUTHORS.rst
pyaf-5.0.dist-info/LICENSE
pyaf-5.0.dist-info/METADATA
pyaf-5.0.dist-info/WHEEL
pyaf-5.0.dist-info/top_level.txt
pyaf-5.0.dist-info/RECORD
