Metadata-Version: 2.1
Name: pyaf
Version: 5.0
Summary: Python Automatic Forecasting
Home-page: https://github.com/antoinecarme/pyaf
Author: Antoine CARME
Author-email: antoine.carme@outlook.com
License: BSD 3-clause
Keywords: arx automatic-forecasting autoregressive benchmark cycle decomposition exogenous forecasting heroku hierarchical-forecasting horizon jupyter pandas python scikit-learn seasonal time-series transformation trend web-service
Classifier: Development Status :: 5 - Production/Stable
Classifier: Programming Language :: Python :: 3
Requires-Python: >=3
License-File: LICENSE
License-File: AUTHORS.rst
Requires-Dist: dill
Requires-Dist: matplotlib
Requires-Dist: pandas
Requires-Dist: pydot
Requires-Dist: scikit-learn
Requires-Dist: scipy
